[{"id": "idols_0", "names": {"ko": "정국", "en": "Jungkook", "ja": "Jungkook", "zh": "Jungkook", "es": "Jungkook"}, "mbti": "ISFP", "description": {"ko": "정국은(는) 당신의 성향(에너지 8, 사교성 7)과 완벽하게 맞아떨어지는 운명의 단짝입니다.", "en": "Jungkook is your destiny, perfectly matching your energy level (8) and sociability (7).", "ja": "Jungkookはあなたの性向（エネルギー8、社交性7）と完璧に一致する運命のパートナーです。", "zh": "Jungkook 是与你的性格（能量 8，社交 7）完美契合的命运伴侣。", "es": "Jungkook es tu destino, coincidiendo perfectamente con tu nivel de energía (8) y sociabilidad (7)."}, "traits": {"energy": 8, "social": 7, "indep": 6, "sense": 8, "play": 7}, "image_url": "https://api.dicebear.com/9.x/micah/png?seed=Jungkook&backgroundColor=ffdfbf"}, {"id": "idols_1", "names": {"ko": "뷔", "en": "V", "ja": "V", "zh": "V", "es": "V"}, "mbti": "INFP", "description": {"ko": "뷔은(는) 당신의 성향(에너지 7, 사교성 8)과 완벽하게 맞아떨어지는 운명의 단짝입니다.", "en": "V is your destiny, perfectly matching your energy level (7) and sociability (8).", "ja": "Vはあなたの性向（エネルギー7、社交性8）と完璧に一致する運命のパートナーです。", "zh": "V 是与你的性格（能量 7，社交 8）完美契合的命运伴侣。", "es": "V es tu destino, coincidiendo perfectamente con tu nivel de energía (7) y sociabilidad (8)."}, "traits": {"energy": 7, "social": 8, "indep": 7, "sense": 9, "play": 8}, "image_url": "https://api.dicebear.com/9.x/micah/png?seed=V&backgroundColor=d1d4f9"}, {"id": "idols_2", "names": {"ko": "제니", "en": "Jennie", "ja": "Jennie", "zh": "Jennie", "es": "Jennie"}, "mbti": "ISTP", "description": {"ko": "제니은(는) 당신의 성향(에너지 6, 사교성 5)과 완벽하게 맞아떨어지는 운명의 단짝입니다.", "en": "Jennie is your destiny, perfectly matching your energy level (6) and sociability (5).", "ja": "Jennieはあなたの性向（エネルギー6、社交性5）と完璧に一致する運命のパートナーです。", "zh": "Jennie 是与你的性格（能量 6，社交 5）完美契合的命运伴侣。", "es": "Jennie es tu destino, coincidiendo perfectamente con tu nivel de energía (6) y sociabilidad (5)."}, "traits": {"energy": 6, "social": 5, "indep": 8, "sense": 7, "play": 6}, "image_url": "https://api.dicebear.com/9.x/micah/png?seed=Jennie&backgroundColor=d1d4f9"}, {"id": "idols_3", "names": {"ko": "장원영", "en": "Wonyoung", "ja": "Wonyoung", "zh": "Wonyoung", "es": "Wonyoung"}, "mbti": "ESFP", "description": {"ko": "장원영은(는) 당신의 성향(에너지 8, 사교성 9)과 완벽하게 맞아떨어지는 운명의 단짝입니다.", "en": "Wonyoung is your destiny, perfectly matching your energy level (8) and sociability (9).", "ja": "Wonyoungはあなたの性向（エネルギー8、社交性9）と完璧に一致する運命のパートナーです。", "zh": "Wonyoung 是与你的性格（能量 8，社交 9）完美契合的命运伴侣。", "es": "Wonyoung es tu destino, coincidiendo perfectamente con tu nivel de energía (8) y sociabilidad (9)."}, "traits": {"energy": 8, "social": 9, "indep": 4, "sense": 7, "play": 9}, "image_url": "https://api.dicebear.com/9.x/micah/png?seed=Wonyoung&backgroundColor=b6e3f4"}, {"id": "idols_4", "names": {"ko": "카리나", "en": "Karina", "ja": "Karina", "zh": "Karina", "es": "Karina"}, "mbti": "ENFP", "description": {"ko": "카리나은(는) 당신의 성향(에너지 7, 사교성 8)과 완벽하게 맞아떨어지는 운명의 단짝입니다.", "en": "Karina is your destiny, perfectly matching your energy level (7) and sociability (8).", "ja": "Karinaはあなたの性向（エネルギー7、社交性8）と完璧に一致する運命のパートナーです。", "zh": "Karina 是与你的性格（能量 7，社交 8）完美契合的命运伴侣。", "es": "Karina es tu destino, coincidiendo perfectamente con tu nivel de energía (7) y sociabilidad (8)."}, "traits": {"energy": 7, "social": 8, "indep": 5, "sense": 8, "play": 7}, "image_url": "https://api.dicebear.com/9.x/micah/png?seed=Karina&backgroundColor=ffdfbf"}, {"id": "idols_5", "names": {"ko": "민지", "en": "Minji", "ja": "Minji", "zh": "Minji", "es": "Minji"}, "mbti": "ESTJ", "description": {"ko": "민지은(는) 당신의 성향(에너지 8, 사교성 7)과 완벽하게 맞아떨어지는 운명의 단짝입니다.", "en": "Minji is your destiny, perfectly matching your energy level (8) and sociability (7).", "ja": "Minjiはあなたの性向（エネルギー8、社交性7）と完璧に一致する運命のパートナーです。", "zh": "Minji 是与你的性格（能量 8，社交 7）完美契合的命运伴侣。", "es": "Minji es tu destino, coincidiendo perfectamente con tu nivel de energía (8) y sociabilidad (7)."}, "traits": {"energy": 8, "social": 7, "indep": 6, "sense": 5, "play": 7}, "image_url": "https://api.dicebear.com/9.x/micah/png?seed=Minji&backgroundColor=d1d4f9"}, {"id": "idols_6", "names": {"ko": "지수", "en": "Jisoo", "ja": "Jisoo", "zh": "Jisoo", "es": "Jisoo"}, "mbti": "ISTJ", "description": {"ko": "지수은(는) 당신의 성향(에너지 6, 사교성 7)과 완벽하게 맞아떨어지는 운명의 단짝입니다.", "en": "Jisoo is your destiny, perfectly matching your energy level (6) and sociability (7).", "ja": "Jisooはあなたの性向（エネルギー6、社交性7）と完璧に一致する運命のパートナーです。", "zh": "Jisoo 是与你的性格（能量 6，社交 7）完美契合的命运伴侣。", "es": "Jisoo es tu destino, coincidiendo perfectamente con tu nivel de energía (6) y sociabilidad (7)."}, "traits": {"energy": 6, "social": 7, "indep": 5, "sense": 5, "play": 6}, "image_url": "https://api.dicebear.com/9.x/micah/png?seed=Jisoo&backgroundColor=ffd5dc"}, {"id": "idols_7", "names": {"ko": "김채원", "en": "Chaewon", "ja": "Chaewon", "zh": "Chaewon", "es": "Chaewon"}, "mbti": "ESTP", "description": {"ko": "김채원은(는) 당신의 성향(에너지 9, 사교성 8)과 완벽하게 맞아떨어지는 운명의 단짝입니다.", "en": "Chaewon is your destiny, perfectly matching your energy level (9) and sociability (8).", "ja": "Chaewonはあなたの性向（エネルギー9、社交性8）と完璧に一致する運命のパートナーです。", "zh": "Chaewon 是与你的性格（能量 9，社交 8）完美契合的命运伴侣。", "es": "Chaewon es tu destino, coincidiendo perfectamente con tu nivel de energía (9) y sociabilidad (8)."}, "traits": {"energy": 9, "social": 8, "indep": 6, "sense": 4, "play": 8}, "image_url": "https://api.dicebear.com/9.x/micah/png?seed=Chaewon&backgroundColor=c0aede"}, {"id": "idols_8", "names": {"ko": "해린", "en": "Haerin", "ja": "Haerin", "zh": "Haerin", "es": "Haerin"}, "mbti": "ISTP", "description": {"ko": "해린은(는) 당신의 성향(에너지 4, 사교성 5)과 완벽하게 맞아떨어지는 운명의 단짝입니다.", "en": "Haerin is your destiny, perfectly matching your energy level (4) and sociability (5).", "ja": "Haerinはあなたの性向（エネルギー4、社交性5）と完璧に一致する運命のパートナーです。", "zh": "Haerin 是与你的性格（能量 4，社交 5）完美契合的命运伴侣。", "es": "Haerin es tu destino, coincidiendo perfectamente con tu nivel de energía (4) y sociabilidad (5)."}, "traits": {"energy": 4, "social": 5, "indep": 8, "sense": 7, "play": 5}, "image_url": "https://api.dicebear.com/9.x/micah/png?seed=Haerin&backgroundColor=ffd5dc"}, {"id": "idols_9", "names": {"ko": "필릭스", "en": "Felix", "ja": "Felix", "zh": "Felix", "es": "Felix"}, "mbti": "ENFP", "description": {"ko": "필릭스은(는) 당신의 성향(에너지 8, 사교성 9)과 완벽하게 맞아떨어지는 운명의 단짝입니다.", "en": "Felix is your destiny, perfectly matching your energy level (8) and sociability (9).", "ja": "Felixはあなたの性向（エネルギー8、社交性9）と完璧に一致する運命のパートナーです。", "zh": "Felix 是与你的性格（能量 8，社交 9）完美契合的命运伴侣。", "es": "Felix es tu destino, coincidiendo perfectamente con tu nivel de energía (8) y sociabilidad (9)."}, "traits": {"energy": 8, "social": 9, "indep": 5, "sense": 8, "play": 7}, "image_url": "https://api.dicebear.com/9.x/micah/png?seed=Felix&backgroundColor=ffd5dc"}]