[{"id": "stars_0", "names": {"ko": "테일러 스위프트", "en": "Taylor Swift", "ja": "Taylor Swift", "zh": "Taylor Swift", "es": "Taylor Swift"}, "mbti": "ENFJ", "description": {"ko": "테일러 스위프트은(는) 당신의 성향(에너지 9, 사교성 8)과 완벽하게 맞아떨어지는 운명의 단짝입니다.", "en": "Taylor Swift is your destiny, perfectly matching your energy level (9) and sociability (8).", "ja": "Taylor Swiftはあなたの性向（エネルギー9、社交性8）と完璧に一致する運命のパートナーです。", "zh": "Taylor Swift 是与你的性格（能量 9，社交 8）完美契合的命运伴侣。", "es": "Taylor Swift es tu destino, coincidiendo perfectamente con tu nivel de energía (9) y sociabilidad (8)."}, "traits": {"energy": 9, "social": 8, "indep": 5, "sense": 9, "play": 7}, "image_url": "https://api.dicebear.com/9.x/micah/png?seed=Taylor%20Swift&backgroundColor=ffd5dc"}, {"id": "stars_1", "names": {"ko": "톰 크루즈", "en": "Tom Cruise", "ja": "Tom Cruise", "zh": "Tom Cruise", "es": "Tom Cruise"}, "mbti": "ESTP", "description": {"ko": "톰 크루즈은(는) 당신의 성향(에너지 10, 사교성 9)과 완벽하게 맞아떨어지는 운명의 단짝입니다.", "en": "Tom Cruise is your destiny, perfectly matching your energy level (10) and sociability (9).", "ja": "Tom Cruiseはあなたの性向（エネルギー10、社交性9）と完璧に一致する運命のパートナーです。", "zh": "Tom Cruise 是与你的性格（能量 10，社交 9）完美契合的命运伴侣。", "es": "Tom Cruise es tu destino, coincidiendo perfectamente con tu nivel de energía (10) y sociabilidad (9)."}, "traits": {"energy": 10, "social": 9, "indep": 7, "sense": 4, "play": 9}, "image_url": "https://api.dicebear.com/9.x/micah/png?seed=Tom%20Cruise&backgroundColor=b6e3f4"}, {"id": "stars_2", "names": {"ko": "레오나르도 디카프리오", "en": "Leonardo DiCaprio", "ja": "Leonardo DiCaprio", "zh": "Leonardo DiCaprio", "es": "Leonardo DiCaprio"}, "mbti": "ESFP", "description": {"ko": "레오나르도 디카프리오은(는) 당신의 성향(에너지 8, 사교성 9)과 완벽하게 맞아떨어지는 운명의 단짝입니다.", "en": "Leonardo DiCaprio is your destiny, perfectly matching your energy level (8) and sociability (9).", "ja": "Leonardo DiCaprioはあなたの性向（エネルギー8、社交性9）と完璧に一致する運命のパートナーです。", "zh": "Leonardo DiCaprio 是与你的性格（能量 8，社交 9）完美契合的命运伴侣。", "es": "Leonardo DiCaprio es tu destino, coincidiendo perfectamente con tu nivel de energía (8) y sociabilidad (9)."}, "traits": {"energy": 8, "social": 9, "indep": 6, "sense": 7, "play": 8}, "image_url": "https://api.dicebear.com/9.x/micah/png?seed=Leonardo%20DiCaprio&backgroundColor=b6e3f4"}, {"id": "stars_3", "names": {"ko": "브래드 피트", "en": "Brad Pitt", "ja": "Brad Pitt", "zh": "Brad Pitt", "es": "Brad Pitt"}, "mbti": "ISFP", "description": {"ko": "브래드 피트은(는) 당신의 성향(에너지 7, 사교성 7)과 완벽하게 맞아떨어지는 운명의 단짝입니다.", "en": "Brad Pitt is your destiny, perfectly matching your energy level (7) and sociability (7).", "ja": "Brad Pittはあなたの性向（エネルギー7、社交性7）と完璧に一致する運命のパートナーです。", "zh": "Brad Pitt 是与你的性格（能量 7，社交 7）完美契合的命运伴侣。", "es": "Brad Pitt es tu destino, coincidiendo perfectamente con tu nivel de energía (7) y sociabilidad (7)."}, "traits": {"energy": 7, "social": 7, "indep": 6, "sense": 6, "play": 7}, "image_url": "https://api.dicebear.com/9.x/micah/png?seed=Brad%20Pitt&backgroundColor=d1d4f9"}, {"id": "stars_4", "names": {"ko": "비욘세", "en": "Beyonce", "ja": "Beyonce", "zh": "Beyonce", "es": "Beyonce"}, "mbti": "ENTJ", "description": {"ko": "비욘세은(는) 당신의 성향(에너지 9, 사교성 8)과 완벽하게 맞아떨어지는 운명의 단짝입니다.", "en": "Beyonce is your destiny, perfectly matching your energy level (9) and sociability (8).", "ja": "Beyonceはあなたの性向（エネルギー9、社交性8）と完璧に一致する運命のパートナーです。", "zh": "Beyonce 是与你的性格（能量 9，社交 8）完美契合的命运伴侣。", "es": "Beyonce es tu destino, coincidiendo perfectamente con tu nivel de energía (9) y sociabilidad (8)."}, "traits": {"energy": 9, "social": 8, "indep": 7, "sense": 5, "play": 8}, "image_url": "https://api.dicebear.com/9.x/micah/png?seed=Beyonce&backgroundColor=ffdfbf"}, {"id": "stars_5", "names": {"ko": "아리아나 그란데", "en": "Ariana Grande", "ja": "Ariana Grande", "zh": "Ariana Grande", "es": "Ariana Grande"}, "mbti": "ESFJ", "description": {"ko": "아리아나 그란데은(는) 당신의 성향(에너지 9, 사교성 9)과 완벽하게 맞아떨어지는 운명의 단짝입니다.", "en": "Ariana Grande is your destiny, perfectly matching your energy level (9) and sociability (9).", "ja": "Ariana Grandeはあなたの性向（エネルギー9、社交性9）と完璧に一致する運命のパートナーです。", "zh": "Ariana Grande 是与你的性格（能量 9，社交 9）完美契合的命运伴侣。", "es": "Ariana Grande es tu destino, coincidiendo perfectamente con tu nivel de energía (9) y sociabilidad (9)."}, "traits": {"energy": 9, "social": 9, "indep": 4, "sense": 8, "play": 8}, "image_url": "https://api.dicebear.com/9.x/micah/png?seed=Ariana%20Grande&backgroundColor=d1d4f9"}, {"id": "stars_6", "names": {"ko": "조니 뎁", "en": "Johnny Depp", "ja": "Johnny Depp", "zh": "Johnny Depp", "es": "Johnny Depp"}, "mbti": "INFP", "description": {"ko": "조니 뎁은(는) 당신의 성향(에너지 4, 사교성 5)과 완벽하게 맞아떨어지는 운명의 단짝입니다.", "en": "Johnny Depp is your destiny, perfectly matching your energy level (4) and sociability (5).", "ja": "Johnny Deppはあなたの性向（エネルギー4、社交性5）と完璧に一致する運命のパートナーです。", "zh": "Johnny Depp 是与你的性格（能量 4，社交 5）完美契合的命运伴侣。", "es": "Johnny Depp es tu destino, coincidiendo perfectamente con tu nivel de energía (4) y sociabilidad (5)."}, "traits": {"energy": 4, "social": 5, "indep": 9, "sense": 9, "play": 6}, "image_url": "https://api.dicebear.com/9.x/micah/png?seed=Johnny%20Depp&backgroundColor=ffd5dc"}, {"id": "stars_7", "names": {"ko": "스칼렛 요한슨", "en": "Scarlett Johansson", "ja": "Scarlett Johansson", "zh": "Scarlett Johansson", "es": "Scarlett Johansson"}, "mbti": "ISTP", "description": {"ko": "스칼렛 요한슨은(는) 당신의 성향(에너지 6, 사교성 7)과 완벽하게 맞아떨어지는 운명의 단짝입니다.", "en": "Scarlett Johansson is your destiny, perfectly matching your energy level (6) and sociability (7).", "ja": "Scarlett Johanssonはあなたの性向（エネルギー6、社交性7）と完璧に一致する運命のパートナーです。", "zh": "Scarlett Johansson 是与你的性格（能量 6，社交 7）完美契合的命运伴侣。", "es": "Scarlett Johansson es tu destino, coincidiendo perfectamente con tu nivel de energía (6) y sociabilidad (7)."}, "traits": {"energy": 6, "social": 7, "indep": 8, "sense": 5, "play": 7}, "image_url": "https://api.dicebear.com/9.x/micah/png?seed=Scarlett%20Johansson&backgroundColor=ffdfbf"}, {"id": "stars_8", "names": {"ko": "로다주", "en": "Robert Downey Jr.", "ja": "Robert Downey Jr.", "zh": "Robert Downey Jr.", "es": "Robert Downey Jr."}, "mbti": "ENTP", "description": {"ko": "로다주은(는) 당신의 성향(에너지 9, 사교성 9)과 완벽하게 맞아떨어지는 운명의 단짝입니다.", "en": "Robert Downey Jr. is your destiny, perfectly matching your energy level (9) and sociability (9).", "ja": "Robert Downey Jr.はあなたの性向（エネルギー9、社交性9）と完璧に一致する運命のパートナーです。", "zh": "Robert Downey Jr. 是与你的性格（能量 9，社交 9）完美契合的命运伴侣。", "es": "Robert Downey Jr. es tu destino, coincidiendo perfectamente con tu nivel de energía (9) y sociabilidad (9)."}, "traits": {"energy": 9, "social": 9, "indep": 6, "sense": 5, "play": 10}, "image_url": "https://api.dicebear.com/9.x/micah/png?seed=Robert%20Downey%20Jr.&backgroundColor=c0aede"}, {"id": "stars_9", "names": {"ko": "엠마 왓슨", "en": "Emma Watson", "ja": "Emma Watson", "zh": "Emma Watson", "es": "Emma Watson"}, "mbti": "ESTJ", "description": {"ko": "엠마 왓슨은(는) 당신의 성향(에너지 8, 사교성 7)과 완벽하게 맞아떨어지는 운명의 단짝입니다.", "en": "Emma Watson is your destiny, perfectly matching your energy level (8) and sociability (7).", "ja": "Emma Watsonはあなたの性向（エネルギー8、社交性7）と完璧に一致する運命のパートナーです。", "zh": "Emma Watson 是与你的性格（能量 8，社交 7）完美契合的命运伴侣。", "es": "Emma Watson es tu destino, coincidiendo perfectamente con tu nivel de energía (8) y sociabilidad (7)."}, "traits": {"energy": 8, "social": 7, "indep": 7, "sense": 6, "play": 5}, "image_url": "https://api.dicebear.com/9.x/micah/png?seed=Emma%20Watson&backgroundColor=b6e3f4"}]